docker_mcp/__init__.py
docker_mcp/docker_executor.py
docker_mcp/handlers.py
docker_mcp/server.py
iflow_mcp_docker_mcp-0.1.1.dist-info/METADATA
iflow_mcp_docker_mcp-0.1.1.dist-info/WHEEL
iflow_mcp_docker_mcp-0.1.1.dist-info/entry_points.txt
iflow_mcp_docker_mcp-0.1.1.dist-info/licenses/LICENSE
iflow_mcp_docker_mcp-0.1.1.dist-info/RECORD
